{"type":"FeatureCollection","features":[{"type":"Feature","geometry":{"type":"MultiPolygon","coordinates":[[[[120.24616861906,23.461255759056],[120.24617505909,23.461328915551],[120.24618214069,23.461402272781],[120.24618213507,23.461403260935],[120.24617204959,23.461406176738],[120.24617082483,23.461395498468],[120.24615625116,23.461245619843],[120.24616861906,23.461255759056]]]]},"properties":{"縣市":"嘉義縣","鄉鎮":"朴子市","路段":"鎮安段","段號":"502-1","ymax":"23.461406176738","ymin":"23.461245619843","xmax":"120.24618214069","xmin":"120.24615625116","xcenter":120.24616919593,"ycenter":23.461325898291,"id":"S1033508","addr":"嘉義縣朴子市鎮安段502-1、502-2地號","area":"37","category":"住宅區","security_deposits":"115,000 ","notes":"地上物狀況為雜草地、鐵條、泥土地、（大同路8號）鐵架棚、水泥地等，以書面方式按現狀點交，地上物概由得標人自理。","stop":"否"}},{"type":"Feature","geometry":null,"properties":{"縣市":"嘉義縣","鄉鎮":"朴子市","路段":"鎮安段","段號":"502-2","ymax":null,"ymin":null,"xmax":null,"xmin":null,"xcenter":0,"ycenter":0,"id":"S1033508","addr":"嘉義縣朴子市鎮安段502-1、502-2地號","area":"37","category":"住宅區","security_deposits":"115,000 ","notes":"地上物狀況為雜草地、鐵條、泥土地、（大同路8號）鐵架棚、水泥地等，以書面方式按現狀點交，地上物概由得標人自理。","stop":"否"}}]}